pydantic_api/notion/models/__init__.py
pydantic_api/notion/models/endpoints/__init__.py
pydantic_api/notion/models/endpoints/base.py
pydantic_api/notion/models/endpoints/blocks.py
pydantic_api/notion/models/endpoints/comments.py
pydantic_api/notion/models/endpoints/databases.py
pydantic_api/notion/models/endpoints/pages.py
pydantic_api/notion/models/endpoints/search.py
pydantic_api/notion/models/endpoints/users.py
pydantic_api/notion/models/objects/__init__.py
pydantic_api/notion/models/objects/block/__init__.py
pydantic_api/notion/models/objects/block/block.py
pydantic_api/notion/models/objects/block/rich_text/__init__.py
pydantic_api/notion/models/objects/block/rich_text/base.py
pydantic_api/notion/models/objects/block/rich_text/equation.py
pydantic_api/notion/models/objects/block/rich_text/mention.py
pydantic_api/notion/models/objects/block/rich_text/rich_text.py
pydantic_api/notion/models/objects/block/rich_text/text.py
pydantic_api/notion/models/objects/comment.py
pydantic_api/notion/models/objects/common.py
pydantic_api/notion/models/objects/database.py
pydantic_api/notion/models/objects/emoji.py
pydantic_api/notion/models/objects/file.py
pydantic_api/notion/models/objects/link_preview.py
pydantic_api/notion/models/objects/page.py
pydantic_api/notion/models/objects/parent.py
pydantic_api/notion/models/objects/properties/__init__.py
pydantic_api/notion/models/objects/properties/common.py
pydantic_api/notion/models/objects/properties/database_property.py
pydantic_api/notion/models/objects/properties/page_property.py
pydantic_api/notion/models/objects/user.py
pydantic_api_models_notion-0.0.23.dist-info/METADATA
pydantic_api_models_notion-0.0.23.dist-info/WHEEL
pydantic_api_models_notion-0.0.23.dist-info/licenses/LICENSE
pydantic_api_models_notion-0.0.23.dist-info/RECORD
